[
  {
    "sessionid": "",
    "tokenid": "",
    "data": {}
  },
  {
    "sessionid": "25c2f384c5c8f6ca66d059b070655410313eeeb3",
    "tokenid": "",
    "data": {}
  },
  {
    "sessionid": "",
    "tokenid": "",
    "data": {}
  },
  {
    "sessionid": "",
    "tokenid": "",
    "data": {}
  },
  {
    "sessionid": "fd2df0d5cfe1838887cdf93f2ddfbce0678d86aa",
    "tokenid": "",
    "data": {}
  },
  {
    "sessionid": "82f42d14de3d879b9e172adcf024f667217b2668",
    "tokenid": "",
    "data": {}
  }
]